LICENSE
NOTICES.rst
aws_custom_ews_kafka_resources/__init__.py
aws_custom_ews_kafka_resources/custom.py
aws_custom_ews_kafka_resources/resource.py
aws_custom_ews_kafka_resources-0.2.0.dist-info/LICENSE
aws_custom_ews_kafka_resources-0.2.0.dist-info/WHEEL
aws_custom_ews_kafka_resources-0.2.0.dist-info/METADATA
aws_custom_ews_kafka_resources-0.2.0.dist-info/RECORD
