Metadata-Version: 2.1
Name: aws-custom-ews-kafka-resources
Version: 0.2.0
Summary: Custom Resources for AWS CloudFormation representing Kafka assets management
License: MPL-2.0
Author: John Preston
Author-email: john@ews-network.net
Requires-Python: >=3.7,<4.0
Classifier: Development Status :: 2 - Pre-Alpha
Classifier: Intended Audience :: Developers
Classifier: Intended Audience :: Information Technology
Classifier: Intended Audience :: System Administrators
Classifier: License :: OSI Approved
Classifier: License :: OSI Approved :: Mozilla Public License 2.0 (MPL 2.0)
Classifier: Programming Language :: Python :: 3
Classifier: Programming Language :: Python :: 3.7
Classifier: Programming Language :: Python :: 3.8
Classifier: Programming Language :: Python :: 3.9
Requires-Dist: tbump (==6.3.1)
Requires-Dist: troposphere (>=3.0,<4.0)
